scullery/__init__.py
scullery/iceflow.py
scullery/jacktools.py
scullery/messagebus.py
scullery/persist.py
scullery/py.typed
scullery/ratelimits.py
scullery/scheduling.py
scullery/snake_compat.py
scullery/statemachines.py
scullery/units.py
scullery/util.py
scullery/words_mnemonic.txt
scullery/workers.py
scullery-0.4.0.dist-info/WHEEL
scullery-0.4.0.dist-info/METADATA
scullery-0.4.0.dist-info/RECORD
