Metadata-Version: 2.4
Name: scullery
Version: 0.4.0
Summary: A utility library based on KaithemAutomation featuring a GStreamer wrapper
Author: Daniel Dunn
License-Expression: LGPL-2.0-or-later
Requires-Dist: pyyaml~=6.0.1
Requires-Dist: pint
Requires-Dist: pyyaml
Requires-Dist: pydantic
Requires-Python: >=3.11
